LICENSE.txt
README.md
setup.cfg
setup.py
learn_python_check/__init__.py
learn_python_check/check_answers.py
learn_python_check.egg-info/PKG-INFO
learn_python_check.egg-info/SOURCES.txt
learn_python_check.egg-info/dependency_links.txt
learn_python_check.egg-info/requires.txt
learn_python_check.egg-info/top_level.txt