Metadata-Version: 2.1
Name: learn-python-check
Version: 1.0.1
Summary: learn python check answers
Home-page: https://github.com/TUDelft-CITG/learn-python-package
Download-URL: https://github.com/TUDelft-CITG/learn-python-package/archive/refs/tags/v1.0.1.tar.gz
Author: Miguel Angel Mendoza-Lugo, Robert Lanzafame, Ahmed Farahat
Author-email: m.a.mendozalugo@tudelft.nl
License: GNU
Project-URL: Bug Tracker, https://github.com/TUDelft-CITG/learn-python-package/issues
Keywords: pypi
Classifier: Development Status :: 3 - Alpha
Classifier: Intended Audience :: Developers
Classifier: Topic :: Software Development :: Documentation
Classifier: License :: OSI Approved :: GNU General Public License v3 (GPLv3)
Classifier: Programming Language :: Python :: 3
Classifier: Programming Language :: Python :: 3.7
Classifier: Programming Language :: Python :: 3.8
Classifier: Programming Language :: Python :: 3.9
License-File: LICENSE.txt
